torchpq/CustomModule.py
torchpq/__init__.py
torchpq/_version.py
torchpq/metric.py
torchpq/util.py
torchpq/clustering/KMeans.py
torchpq/clustering/KMeansOld.py
torchpq/clustering/MinibatchKMeans.py
torchpq/clustering/MultiKMeans.py
torchpq/clustering/MultiKMeansOld.py
torchpq/clustering/__init__.py
torchpq/codec/BaseCodec.py
torchpq/codec/PQCodec.py
torchpq/codec/SQCodec.py
torchpq/codec/VQCodec.py
torchpq/codec/__init__.py
torchpq/container/BaseContainer.py
torchpq/container/CellContainer.py
torchpq/container/DistributedCellContainer.py
torchpq/container/FlatContainer.py
torchpq/container/FlatContainerGroup.py
torchpq/container/__init__.py
torchpq/experimental/IVFMPQ.py
torchpq/experimental/MPQ.py
torchpq/experimental/__init__.py
torchpq/fn/IVFPQTopk.py
torchpq/fn/Topk.py
torchpq/fn/__init__.py
torchpq/index/BaseIndex.py
torchpq/index/FlatIndex.py
torchpq/index/IVFPQIndex.py
torchpq/index/IVFPQRIndex.py
torchpq/index/__init__.py
torchpq/kernels/BMMCuda.py
torchpq/kernels/ComputeCentroidsCuda.py
torchpq/kernels/ComputeProductCuda.py
torchpq/kernels/CustomKernel.py
torchpq/kernels/DistributedIVFPQTop1Cuda.py
torchpq/kernels/DistributedIVFPQTopkCuda.py
torchpq/kernels/GetAddressByIDCuda.py
torchpq/kernels/GetDivByAddressCuda.py
torchpq/kernels/GetDivByAddressV2Cuda.py
torchpq/kernels/GetIOACuda.py
torchpq/kernels/GetWriteAddressCuda.py
torchpq/kernels/GetWriteAddressV2Cuda.py
torchpq/kernels/IVFPQ4Top1Cuda_v1.py
torchpq/kernels/IVFPQTop1Cuda.py
torchpq/kernels/IVFPQTop1Cuda_v2.py
torchpq/kernels/IVFPQTopkCuda.py
torchpq/kernels/MBMMCuda.py
torchpq/kernels/MaxSimCuda.py
torchpq/kernels/MinBMMCuda.py
torchpq/kernels/PQDecodeCuda.py
torchpq/kernels/Top1SelectCuda.py
torchpq/kernels/Top32SelectCuda.py
torchpq/kernels/TopkBMMCuda.py
torchpq/kernels/TopkSelectCuda.py
torchpq/kernels/TopkSelectCuda_v2.py
torchpq/kernels/__init__.py
torchpq/kernels/default_device.py
torchpq/kernels/cuda/bmm.cu
torchpq/kernels/cuda/bmm_helpers.cu
torchpq/kernels/cuda/compute_centroids.cu
torchpq-0.3.0.6.dist-info/LICENSE
torchpq-0.3.0.6.dist-info/METADATA
torchpq-0.3.0.6.dist-info/WHEEL
torchpq-0.3.0.6.dist-info/top_level.txt
torchpq-0.3.0.6.dist-info/RECORD
