Metadata-Version: 2.1
Name: torchpq
Version: 0.3.0.6
Summary: Efficient implementations of Product Quantization and its variants
Home-page: https://github.com/DeMoriarty/TorchPQ
Download-URL: https://github.com/DeMoriarty/TorchPQ/archive/v_0306.tar.gz
Author: demoriarty
Author-email: sahbanjan@gmail.com
License: MIT
Keywords: KMeans,K-means,ANN,pytorch,machine learning,pq,product quantization,IVFPQ,approximate nearest neighbors
Classifier: Development Status :: 3 - Alpha
Classifier: Intended Audience :: Developers
Classifier: Topic :: Software Development :: Build Tools
Classifier: License :: OSI Approved :: MIT License
Classifier: Programming Language :: Python :: 3
Classifier: Programming Language :: Python :: 3.4
Classifier: Programming Language :: Python :: 3.5
Classifier: Programming Language :: Python :: 3.6
Classifier: Programming Language :: Python :: 3.7
Classifier: Programming Language :: Python :: 3.8
Classifier: Programming Language :: Python :: 3.9
License-File: LICENSE
Requires-Dist: numpy
Requires-Dist: torch
